pact_broker/__init__.py
pact_broker/cli.py
pact_broker/client.py
pact_broker/settings.py
pact_broker/urls.py
pact_broker_client-2.0.0.dist-info/DESCRIPTION.rst
pact_broker_client-2.0.0.dist-info/METADATA
pact_broker_client-2.0.0.dist-info/RECORD
pact_broker_client-2.0.0.dist-info/WHEEL
pact_broker_client-2.0.0.dist-info/entry_points.txt
pact_broker_client-2.0.0.dist-info/metadata.json
pact_broker_client-2.0.0.dist-info/top_level.txt
