Metadata-Version: 2.0
Name: pact-broker-client
Version: 2.0.0
Summary: UNKNOWN
Home-page: UNKNOWN
Author: Babylon Health
Author-email: chatbot-developers@babylonhealth.com
License: Apache 2.0
Platform: UNKNOWN
Classifier: Programming Language :: Python :: 3.6
Requires-Dist: click (==6.7)
Requires-Dist: requests (>=2.0.0,<3.0.0)
